{
    "key": "group_why_it_works",
    "title": "Блок: Чому це працює?",
    "fields": [
        {
            "key": "field_why_it_works_title",
            "label": "Заголовок секції",
            "name": "title",
            "type": "text",
            "default_value": "ЧОМУ ЦЕ ПРАЦЮЄ?"
        },
        {
            "key": "field_why_it_works_cards",
            "label": "Картки",
            "name": "cards",
            "type": "repeater",
            "layout": "block",
            "button_label": "Додати картку",
            "sub_fields": [
                {
                    "key": "field_why_it_works_card_icon",
                    "label": "Іконка (SVG код)",
                    "name": "icon",
                    "type": "textarea",
                    "instructions": "Вставте SVG-код іконки для кращого перформансу",
                    "rows": 4
                },
                {
                    "key": "field_why_it_works_card_title",
                    "label": "Заголовок картки",
                    "name": "card_title",
                    "type": "text"
                },
                {
                    "key": "field_why_it_works_card_text",
                    "label": "Опис",
                    "name": "card_text",
                    "type": "textarea",
                    "rows": 3
                }
            ]
        }
    ],
    "location": [
        [
            {
                "param": "block",
                "operator": "==",
                "value": "acf/why-it-works"
            }
        ]
    ],
    "active": true
}
